artifact/__init__.py
artifact/__main__.py
artifact/visuals/cat/cat_dead.png
artifact/visuals/cat/cat_normal.png
artifact/visuals/cat/cat_start.png
artifact/visuals/cat/cat_walk.png
artifact/visuals/obsticles/rock.png
artifact/visuals/obsticles/water.png
artifact/visuals/other/game_over.png
artifact/visuals/other/line.png
artifact/visuals/other/restart.png
template_python_project_poetry-1.0.0.dist-info/METADATA
template_python_project_poetry-1.0.0.dist-info/WHEEL
template_python_project_poetry-1.0.0.dist-info/entry_points.txt
template_python_project_poetry-1.0.0.dist-info/licenses/LICENSE
template_python_project_poetry-1.0.0.dist-info/RECORD
