Metadata-Version: 2.4
Name: template-python-project-poetry
Version: 1.0.0
Summary: A template for Python projects, using Poetry
License: Apache 2.0
License-File: LICENSE
Author: Giovanni Ciatto
Author-email: giovanni.ciatto@unibo.it
Requires-Python: >=3.9.0,<4.0.0
Classifier: License :: Other/Proprietary License
Classifier: Programming Language :: Python :: 3
Classifier: Programming Language :: Python :: 3.9
Classifier: Programming Language :: Python :: 3.10
Classifier: Programming Language :: Python :: 3.11
Classifier: Programming Language :: Python :: 3.12
Classifier: Programming Language :: Python :: 3.13
Classifier: Programming Language :: Python :: 3.14
